{
  "title": "Our Services",
  "text": "If you offer a variety of services or products, organize them into categories for easy navigation. Each category can have a brief description and a link to view more details.",
  "section": [
    {
      "title": "ERP Solutions",
      "content": "Comprehensive ERP implementation services tailored to your business needs.",
      "icon": "custom-business.svg"
    },
    {
      "title": "AI Integration",
      "content": "Leverage AI for smarter business processes.",
      "icon": "supply-chain.svg"
    },
    {
      "title": "CRM Solutions",
      "content": "Optimize customer relationships with our CRM solutions. ",
      "icon": "crm.svg"
    },
    {
      "title": "Business Consulting",
      "content": "Expert consulting to enhance your business operations. ",
      "icon": "project-mngmt.svg"
    }
  ],
  "callToAction": "Explore\n our \nServices"
}